aiblock/__init__.py
aiblock/_version.py
aiblock/blockchain.py
aiblock/config.py
aiblock/constants.py
aiblock/interfaces.py
aiblock/key_handler.py
aiblock/py.typed
aiblock/validators.py
aiblock/wallet.py
aiblock/utils/__init__.py
aiblock/utils/general_utils.py
aiblock-0.2.9.dist-info/licenses/LICENSE
aiblock-0.2.9.dist-info/METADATA
aiblock-0.2.9.dist-info/WHEEL
aiblock-0.2.9.dist-info/top_level.txt
aiblock-0.2.9.dist-info/RECORD
