Metadata-Version: 2.4
Name: aiblock
Version: 0.2.9
Summary: Python SDK for interacting with the AIBlock blockchain
Author-email: AIBlock Team <team@aiblock.dev>
License: MIT License
Project-URL: Homepage, https://github.com/AIBlockOfficial/2Way.py
Project-URL: Documentation, https://github.com/AIBlockOfficial/2Way.py/tree/main/docs
Project-URL: Bug Tracker, https://github.com/AIBlockOfficial/2Way.py/issues
Keywords: blockchain,aiblock,cryptocurrency
Classifier: Development Status :: 4 - Beta
Classifier: Intended Audience :: Developers
Classifier: Programming Language :: Python :: 3
Classifier: Programming Language :: Python :: 3.8
Classifier: Programming Language :: Python :: 3.9
Classifier: Programming Language :: Python :: 3.10
Classifier: Programming Language :: Python :: 3.11
Classifier: License :: OSI Approved :: MIT License
Classifier: Operating System :: OS Independent
Classifier: Topic :: Software Development :: Libraries :: Python Modules
Classifier: Topic :: Security :: Cryptography
Requires-Python: >=3.8
License-File: LICENSE
Requires-Dist: requests>=2.25.1
Requires-Dist: pynacl>=1.4.0
Requires-Dist: mnemonic>=0.20
Requires-Dist: typing-extensions>=4.0.0
Requires-Dist: base58>=2.1.1
Requires-Dist: python-dotenv>=1.0.0
Requires-Dist: bip32utils>=0.3.0
Dynamic: license-file
